publish_test_0118/__init__.py
publish_test_0118/dynbatch/__init__.py
publish_test_0118/dynbatch/base.py
publish_test_0118/dynbatch/batch.py
publish_test_0118/rlog/__init__.py
publish_test_0118/rlog/eventhub.py
publish_test_0118/rlog/log.py
publish_test_0118/rlog/logimp.py
publish_test_0118-0.1.11.dist-info/METADATA
publish_test_0118-0.1.11.dist-info/entry_points.txt
publish_test_0118-0.1.11.dist-info/WHEEL
publish_test_0118-0.1.11.dist-info/RECORD
