Metadata-Version: 2.1
Name: publish-test-0118
Version: 0.1.11
Summary: 
Author: Xiaodong Yang
Author-email: xiaoyan@microsoft.com
Requires-Python: >=3.9,<4.0
Classifier: Programming Language :: Python :: 3
Classifier: Programming Language :: Python :: 3.9
Classifier: Programming Language :: Python :: 3.10
Classifier: Programming Language :: Python :: 3.11
Requires-Dist: azure-eventhub (>=5.10.1,<6.0.0)
Requires-Dist: azure-identity (>=1.7.0,<2.0.0)
Requires-Dist: dataclasses-json (>=0.5.7,<0.6.0)
Requires-Dist: typeguard (>=2.13.3,<3.0.0)
